{
	"configurations" : 
	[
		{
			"directories" : 
			[
				{
					"build" : ".",
					"minimumCMakeVersion" : 
					{
						"string" : "3.10"
					},
					"projectIndex" : 0,
					"source" : ".",
					"targetIndexes" : 
					[
						0
					]
				}
			],
			"name" : "",
			"projects" : 
			[
				{
					"directoryIndexes" : 
					[
						0
					],
					"name" : "Preprocess",
					"targetIndexes" : 
					[
						0
					]
				}
			],
			"targets" : 
			[
				{
					"directoryIndex" : 0,
					"id" : "Preprocess::@6890427a1f51a3e7e1df",
					"jsonFile" : "target-Preprocess-58075f23c8751dbb9848.json",
					"name" : "Preprocess",
					"projectIndex" : 0
				}
			]
		}
	],
	"kind" : "codemodel",
	"paths" : 
	{
		"build" : "/home/user/Preprocess/build",
		"source" : "/home/user/Preprocess"
	},
	"version" : 
	{
		"major" : 2,
		"minor" : 0
	}
}
